<annotation>
	<folder>images</folder>
	<filename>img0103.jpg</filename>
	<path>C:\Users\Yanske\Desktop\Misaligned_shelves\images\img0103.jpg</path>
	<source>
		<database>Unknown</database>
	</source>
	<size>
		<width>2340</width>
		<height>4160</height>
		<depth>3</depth>
	</size>
	<segmented>0</segmented>
	<object>
		<name>misalignment</name>
		<pose>Unspecified</pose>
		<truncated>0</truncated>
		<difficult>0</difficult>
		<bndbox>
			<xmin>214</xmin>
			<ymin>3502</ymin>
			<xmax>272</xmax>
			<ymax>3681</ymax>
		</bndbox>
	</object>
	<object>
		<name>misalignment</name>
		<pose>Unspecified</pose>
		<truncated>0</truncated>
		<difficult>0</difficult>
		<bndbox>
			<xmin>279</xmin>
			<ymin>3479</ymin>
			<xmax>364</xmax>
			<ymax>3676</ymax>
		</bndbox>
	</object>
	<object>
		<name>misalignment</name>
		<pose>Unspecified</pose>
		<truncated>0</truncated>
		<difficult>0</difficult>
		<bndbox>
			<xmin>1660</xmin>
			<ymin>2114</ymin>
			<xmax>1760</xmax>
			<ymax>2164</ymax>
		</bndbox>
	</object>
	<object>
		<name>misalignment</name>
		<pose>Unspecified</pose>
		<truncated>0</truncated>
		<difficult>0</difficult>
		<bndbox>
			<xmin>1005</xmin>
			<ymin>2676</ymin>
			<xmax>1202</xmax>
			<ymax>2800</ymax>
		</bndbox>
	</object>
	<object>
		<name>misalignment</name>
		<pose>Unspecified</pose>
		<truncated>0</truncated>
		<difficult>0</difficult>
		<bndbox>
			<xmin>795</xmin>
			<ymin>2671</ymin>
			<xmax>1002</xmax>
			<ymax>2788</ymax>
		</bndbox>
	</object>
	<object>
		<name>misalignment</name>
		<pose>Unspecified</pose>
		<truncated>0</truncated>
		<difficult>0</difficult>
		<bndbox>
			<xmin>1588</xmin>
			<ymin>2688</ymin>
			<xmax>1807</xmax>
			<ymax>2793</ymax>
		</bndbox>
	</object>
	<object>
		<name>misalignment</name>
		<pose>Unspecified</pose>
		<truncated>0</truncated>
		<difficult>0</difficult>
		<bndbox>
			<xmin>364</xmin>
			<ymin>3507</ymin>
			<xmax>460</xmax>
			<ymax>3705</ymax>
		</bndbox>
	</object>
</annotation>
