<annotation>
	<folder>images</folder>
	<filename>img0921.jpg</filename>
	<path>C:\Users\Yanske\Desktop\Misaligned_shelves\images\img0921.jpg</path>
	<source>
		<database>Unknown</database>
	</source>
	<size>
		<width>3120</width>
		<height>4208</height>
		<depth>3</depth>
	</size>
	<segmented>0</segmented>
	<object>
		<name>misalignment</name>
		<pose>Unspecified</pose>
		<truncated>0</truncated>
		<difficult>0</difficult>
		<bndbox>
			<xmin>252</xmin>
			<ymin>3062</ymin>
			<xmax>578</xmax>
			<ymax>3383</ymax>
		</bndbox>
	</object>
	<object>
		<name>misalignment</name>
		<pose>Unspecified</pose>
		<truncated>0</truncated>
		<difficult>0</difficult>
		<bndbox>
			<xmin>2841</xmin>
			<ymin>2687</ymin>
			<xmax>3109</xmax>
			<ymax>2805</ymax>
		</bndbox>
	</object>
</annotation>
