<annotation>
	<folder>images</folder>
	<filename>img0017.jpg</filename>
	<path>C:\Users\kingh\Desktop\images\img0017.jpg</path>
	<source>
		<database>Unknown</database>
	</source>
	<size>
		<width>2368</width>
		<height>4224</height>
		<depth>3</depth>
	</size>
	<segmented>0</segmented>
	<object>
		<name>empty</name>
		<pose>Unspecified</pose>
		<truncated>0</truncated>
		<difficult>0</difficult>
		<bndbox>
			<xmin>1702</xmin>
			<ymin>874</ymin>
			<xmax>2102</xmax>
			<ymax>1033</ymax>
		</bndbox>
	</object>
	<object>
		<name>empty</name>
		<pose>Unspecified</pose>
		<truncated>0</truncated>
		<difficult>0</difficult>
		<bndbox>
			<xmin>1612</xmin>
			<ymin>1781</ymin>
			<xmax>2012</xmax>
			<ymax>1940</ymax>
		</bndbox>
	</object>
	<object>
		<name>empty</name>
		<pose>Unspecified</pose>
		<truncated>0</truncated>
		<difficult>0</difficult>
		<bndbox>
			<xmin>1702</xmin>
			<ymin>1342</ymin>
			<xmax>2252</xmax>
			<ymax>1499</ymax>
		</bndbox>
	</object>
	<object>
		<name>empty</name>
		<pose>Unspecified</pose>
		<truncated>0</truncated>
		<difficult>0</difficult>
		<bndbox>
			<xmin>883</xmin>
			<ymin>2653</ymin>
			<xmax>1315</xmax>
			<ymax>2770</ymax>
		</bndbox>
	</object>
	<object>
		<name>empty</name>
		<pose>Unspecified</pose>
		<truncated>0</truncated>
		<difficult>0</difficult>
		<bndbox>
			<xmin>1773</xmin>
			<ymin>2667</ymin>
			<xmax>2115</xmax>
			<ymax>2787</ymax>
		</bndbox>
	</object>
</annotation>
