<annotation>
	<folder>images</folder>
	<filename>img0210.jpg</filename>
	<path>C:\Users\kingh\Desktop\images\img0210.jpg</path>
	<source>
		<database>Unknown</database>
	</source>
	<size>
		<width>3264</width>
		<height>2448</height>
		<depth>3</depth>
	</size>
	<segmented>0</segmented>
	<object>
		<name>empty</name>
		<pose>Unspecified</pose>
		<truncated>0</truncated>
		<difficult>0</difficult>
		<bndbox>
			<xmin>33</xmin>
			<ymin>530</ymin>
			<xmax>287</xmax>
			<ymax>743</ymax>
		</bndbox>
	</object>
	<object>
		<name>empty</name>
		<pose>Unspecified</pose>
		<truncated>0</truncated>
		<difficult>0</difficult>
		<bndbox>
			<xmin>294</xmin>
			<ymin>533</ymin>
			<xmax>591</xmax>
			<ymax>743</ymax>
		</bndbox>
	</object>
	<object>
		<name>empty</name>
		<pose>Unspecified</pose>
		<truncated>0</truncated>
		<difficult>0</difficult>
		<bndbox>
			<xmin>1065</xmin>
			<ymin>547</ymin>
			<xmax>1245</xmax>
			<ymax>758</ymax>
		</bndbox>
	</object>
	<object>
		<name>empty</name>
		<pose>Unspecified</pose>
		<truncated>0</truncated>
		<difficult>0</difficult>
		<bndbox>
			<xmin>1257</xmin>
			<ymin>541</ymin>
			<xmax>1437</xmax>
			<ymax>752</ymax>
		</bndbox>
	</object>
	<object>
		<name>empty</name>
		<pose>Unspecified</pose>
		<truncated>0</truncated>
		<difficult>0</difficult>
		<bndbox>
			<xmin>835</xmin>
			<ymin>826</ymin>
			<xmax>1015</xmax>
			<ymax>1037</ymax>
		</bndbox>
	</object>
	<object>
		<name>empty</name>
		<pose>Unspecified</pose>
		<truncated>0</truncated>
		<difficult>0</difficult>
		<bndbox>
			<xmin>182</xmin>
			<ymin>829</ymin>
			<xmax>362</xmax>
			<ymax>1040</ymax>
		</bndbox>
	</object>
	<object>
		<name>empty</name>
		<pose>Unspecified</pose>
		<truncated>0</truncated>
		<difficult>0</difficult>
		<bndbox>
			<xmin>1297</xmin>
			<ymin>1425</ymin>
			<xmax>1413</xmax>
			<ymax>1660</ymax>
		</bndbox>
	</object>
	<object>
		<name>empty</name>
		<pose>Unspecified</pose>
		<truncated>0</truncated>
		<difficult>0</difficult>
		<bndbox>
			<xmin>848</xmin>
			<ymin>1426</ymin>
			<xmax>943</xmax>
			<ymax>1665</ymax>
		</bndbox>
	</object>
	<object>
		<name>empty</name>
		<pose>Unspecified</pose>
		<truncated>0</truncated>
		<difficult>0</difficult>
		<bndbox>
			<xmin>2443</xmin>
			<ymin>589</ymin>
			<xmax>2576</xmax>
			<ymax>846</ymax>
		</bndbox>
	</object>
	<object>
		<name>empty</name>
		<pose>Unspecified</pose>
		<truncated>0</truncated>
		<difficult>0</difficult>
		<bndbox>
			<xmin>2756</xmin>
			<ymin>926</ymin>
			<xmax>2889</xmax>
			<ymax>1183</ymax>
		</bndbox>
	</object>
</annotation>
